odoo/addons/ssi_revenue_recognition_project/README.rst
odoo/addons/ssi_revenue_recognition_project/__init__.py
odoo/addons/ssi_revenue_recognition_project/__manifest__.py
odoo/addons/ssi_revenue_recognition_project/models/__init__.py
odoo/addons/ssi_revenue_recognition_project/models/service_contract_fix_item.py
odoo/addons/ssi_revenue_recognition_project/models/service_contract_performance_obligation.py
odoo/addons/ssi_revenue_recognition_project/models/service_type.py
odoo/addons/ssi_revenue_recognition_project/static/description/banner.png
odoo/addons/ssi_revenue_recognition_project/static/description/icon.png
odoo/addons/ssi_revenue_recognition_project/views/service_contract_performance_obligation_views.xml
odoo/addons/ssi_revenue_recognition_project/views/service_type_views.xml
odoo14_addon_ssi_revenue_recognition_project-14.0.1.1.1.dist-info/METADATA
odoo14_addon_ssi_revenue_recognition_project-14.0.1.1.1.dist-info/WHEEL
odoo14_addon_ssi_revenue_recognition_project-14.0.1.1.1.dist-info/top_level.txt
odoo14_addon_ssi_revenue_recognition_project-14.0.1.1.1.dist-info/RECORD
